frosty/__init__.py
frosty/frosty.py
frosty_dag-0.0.2.dist-info/LICENSE
frosty_dag-0.0.2.dist-info/METADATA
frosty_dag-0.0.2.dist-info/WHEEL
frosty_dag-0.0.2.dist-info/top_level.txt
frosty_dag-0.0.2.dist-info/RECORD
